seq_dector_1011/seq_det.vhdl
library ieee;
use ieee.std_logic_1164.all;

entity seq_det is
	port(
		clk, reset, seq: in std_logic;
		det: out std_logic
	);
end seq_det;

architecture behaviour of seq_det is
	type state_type is (a, b, c, d); -- Defines the type for states in state machine
	signal state: state_type:= a;

begin
	process(clk)
	begin
		if reset = '1' then
			det <= '0';
			state <= a;
		elsif rising_edge(clk) then
			case state is
				when a =>
					det <= '0';
					if seq = '0' then 
						state <= a;
					else
						state <= b;
					end if;
				when c =>
					if seq ='0' then
						state <= a;
					else
						state <= d;
					end if;
				when d =>
					if seq = '0' then
						state <= c;
					else
						state <= a;
						det <= '1';
					end if;
				when others =>
					NULL;
			end case;
		end if;
	end process;
end behaviour;

seq_dector_1011/seq_det_tb.vhdl
library ieee;
use ieee.std_logic_1164.all;

entity seq_det_tb is
end seq_det_tb;

architecture behaviour of seq_det_tb is
	signal clk, reset, seq, det: std_logic := '0';
	constant clk_period: time := 50 ns;

begin
	uut: entity work.seq_det port map(
		clk => clk,
		reset => reset,
		seq => seq,
		det => det
	);

	clk_proc:
	process
	begin
		clk <= '0';
		wait for clk_period;
		clk <= '1';
		wait for clk_period;
	end process;

	stim_proc:
	process
	begin
		seq <= '1';           	--1
      		wait for clk_period;
        	
		seq <= '1';             --11
      		wait for clk_period;
        	
		seq <= '0';             --110
      		wait for clk_period;
        	
		seq <= '1';             --1101
      		wait for clk_period;
        	
		seq <= '1';             --11011
     		wait for clk_period;
      	  	
		seq <= '1';             --110111
      		wait for clk_period;
        	
		seq <= '0';             --1101110
      		wait for clk_period;
        	
		seq <= '1';             --11011101
      		wait for clk_period;
        	
		seq <= '0';             --110111010
      		wait for clk_period;
        	
		seq <= '1';             --1101110101
      		wait for clk_period;
      		wait;
	end process;
end behaviour;

seq_dector_1011/result.vcd
$date
  Mon Feb  5 19:39:53 2024
$end
$version
  GHDL v0
$end
$timescale
  1 fs
$end
$scope module standard $end
$upscope $end
$scope module std_logic_1164 $end
$upscope $end
$scope module seq_det_tb $end
$var reg 1 ! clk $end
$var reg 1 " reset $end
$var reg 1 # seq $end
$var reg 1 $ det $end
$scope module uut $end
$var reg 1 % clk $end
$var reg 1 & reset $end
$var reg 1 ' seq $end
$var reg 1 ( det $end
$comment state is not handled $end
$upscope $end
$upscope $end
$enddefinitions $end
#0
0!
0"
1#
U$
0%
0&
1'
U(
#50000000
1!
0$
1%
0(
#100000000
0!
0#
0%
0'
#150000000
1!
1#
1%
1'
#200000000
0!
0%
#250000000
1!
1%
#300000000
0!
0#
0%
0'
#350000000
1!
1#
1%
1'
#400000000
0!
0#
0%
0'
#450000000
1!
1#
1%
1'
